<?xml version="1.0" encoding="UTF-8"?>

<!-- generated on 2025-05-04 13:39:45 by Eclipse SUMO sumo Version 1.20.0
<configuration xmlns:xsi="http://www.w3.org/2001/XMLSchema-instance" xsi:noNamespaceSchemaLocation="http://sumo.dlr.de/xsd/sumoConfiguration.xsd">

    <input>
        <net-file value="map.net.xml"/>
        <route-files value="demand.rou.alt.xml"/>
    </input>

    <output>
        <summary-output value="summary_out.xml"/>
        <tripinfo-output value="tripinfo.xml"/>
        <statistic-output value="statistic_out.xml"/>
    </output>

    <time>
        <step-length value="0.5"/>
    </time>

    <processing>
        <lateral-resolution value="0.2"/>
        <ignore-junction-blocker value="300"/>
        <collision.action value="none"/>
    </processing>

    <traci_server>
        <remote-port value="49919"/>
    </traci_server>

</configuration>
-->

<statistics xmlns:xsi="http://www.w3.org/2001/XMLSchema-instance" xsi:noNamespaceSchemaLocation="http://sumo.dlr.de/xsd/statistic_file.xsd">
    <performance clockBegin="4271.78" clockEnd="8749.07" clockDuration="4477.29" traciDuration="2690.07" realTimeFactor="3.34" vehicleUpdatesPerSecond="7261.91" personUpdatesPerSecond="0.00" begin="0.00" end="14962.00" duration="14962.00"/>
    <vehicles loaded="82128" inserted="82128" running="0" waiting="0"/>
    <teleports total="22" jam="0" yield="22" wrongLane="0"/>
    <safety collisions="0" emergencyStops="0" emergencyBraking="0"/>
    <persons loaded="0" running="0" jammed="0"/>
    <personTeleports total="0" abortWait="0" wrongDest="0"/>
    <vehicleTripStatistics count="82128" routeLength="945.50" speed="6.99" duration="197.94" waitingTime="105.16" timeLoss="129.06" departDelay="87.77" departDelayWaiting="-1.00" totalTravelTime="16256832.00" totalDepartDelay="7208395.89"/>
    <pedestrianStatistics number="0" routeLength="0.00" duration="0.00" timeLoss="0.00"/>
    <rideStatistics number="0"/>
    <transportStatistics number="0"/>
</statistics>
