<?xml version="1.0" encoding="UTF-8"?>

<!-- generated on 2025-05-12 01:53:14 by Eclipse SUMO sumo Version 1.22.0
<sumoConfiguration xmlns:xsi="http://www.w3.org/2001/XMLSchema-instance" xsi:noNamespaceSchemaLocation="http://sumo.dlr.de/xsd/sumoConfiguration.xsd">

    <input>
        <net-file value="map.net.xml"/>
        <route-files value="demand.rou.alt.xml"/>
        <additional-files value="detector_temp_20250512_015313.add.xml"/>
    </input>

    <output>
        <summary-output value="results/20250512_015313/summary_out_20250512_015313.xml"/>
        <tripinfo-output value="results/20250512_015313/tripinfo_out_20250512_015313.xml"/>
        <statistic-output value="results/20250512_015313/statistic_out_20250512_015313.xml"/>
    </output>

    <processing>
        <threads value="4"/>
        <lateral-resolution value="0.2"/>
        <ignore-junction-blocker value="300"/>
        <collision.action value="none"/>
    </processing>

    <traci_server>
        <remote-port value="51069"/>
    </traci_server>

</sumoConfiguration>
-->

<summary xmlns:xsi="http://www.w3.org/2001/XMLSchema-instance" xsi:noNamespaceSchemaLocation="http://sumo.dlr.de/xsd/summary_file.xsd">
    <step time="0.00" loaded="67" inserted="59" running="59" waiting="7" ended="0" arrived="0" collisions="0" teleports="0" halting="0" stopped="0" meanWaitingTime="0.00" meanTravelTime="-1.00" meanSpeed="13.52" meanSpeedRelative="0.97" duration="1"/>
    <step time="1.00" loaded="67" inserted="60" running="60" waiting="6" ended="0" arrived="0" collisions="0" teleports="0" halting="0" stopped="0" meanWaitingTime="0.02" meanTravelTime="-1.00" meanSpeed="13.07" meanSpeedRelative="0.94" duration="4"/>
    <step time="2.00" loaded="934" inserted="63" running="63" waiting="5" ended="0" arrived="0" collisions="0" teleports="0" halting="0" stopped="0" meanWaitingTime="0.08" meanTravelTime="-1.00" meanSpeed="12.45" meanSpeedRelative="0.90" duration="99"/>
    <step time="3.00" loaded="934" inserted="70" running="70" waiting="2" ended="0" arrived="0" collisions="0" teleports="0" halting="0" stopped="0" meanWaitingTime="0.26" meanTravelTime="-1.00" meanSpeed="11.72" meanSpeedRelative="0.84" duration="2"/>
    <step time="4.00" loaded="934" inserted="74" running="74" waiting="1" ended="0" arrived="0" collisions="0" teleports="0" halting="1" stopped="0" meanWaitingTime="0.34" meanTravelTime="-1.00" meanSpeed="11.30" meanSpeedRelative="0.81" duration="2"/>
    <step time="5.00" loaded="934" inserted="78" running="78" waiting="0" ended="0" arrived="0" collisions="0" teleports="0" halting="2" stopped="0" meanWaitingTime="0.42" meanTravelTime="-1.00" meanSpeed="11.02" meanSpeedRelative="0.79" duration="3"/>
    <step time="6.00" loaded="934" inserted="82" running="82" waiting="0" ended="0" arrived="0" collisions="0" teleports="0" halting="1" stopped="0" meanWaitingTime="0.45" meanTravelTime="-1.00" meanSpeed="11.31" meanSpeedRelative="0.81" duration="2"/>
    <step time="7.00" loaded="934" inserted="85" running="85" waiting="0" ended="0" arrived="0" collisions="0" teleports="0" halting="2" stopped="0" meanWaitingTime="0.47" meanTravelTime="-1.00" meanSpeed="11.33" meanSpeedRelative="0.82" duration="3"/>
    <step time="8.00" loaded="934" inserted="88" running="88" waiting="0" ended="0" arrived="0" collisions="0" teleports="0" halting="3" stopped="0" meanWaitingTime="0.49" meanTravelTime="-1.00" meanSpeed="11.31" meanSpeedRelative="0.81" duration="3"/>
    <step time="9.00" loaded="934" inserted="91" running="91" waiting="0" ended="0" arrived="0" collisions="0" teleports="0" halting="3" stopped="0" meanWaitingTime="0.51" meanTravelTime="-1.00" meanSpeed="11.37" meanSpeedRelative="0.82" duration="6"/>
    <step time="10.00" loaded="934" inserted="94" running="94" waiting="0" ended="0" arrived="0" collisions="0" teleports="0" halting="4" stopped="0" meanWaitingTime="0.52" meanTravelTime="-1.00" meanSpeed="11.16" meanSpeedRelative="0.80" duration="4"/>
    <step time="11.00" loaded="934" inserted="100" running="100" waiting="0" ended="0" arrived="0" collisions="0" teleports="0" halting="5" stopped="0" meanWaitingTime="0.55" meanTravelTime="-1.00" meanSpeed="11.21" meanSpeedRelative="0.81" duration="4"/>
    <step time="12.00" loaded="934" inserted="106" running="106" waiting="0" ended="0" arrived="0" collisions="0" teleports="0" halting="5" stopped="0" meanWaitingTime="0.58" meanTravelTime="-1.00" meanSpeed="11.33" meanSpeedRelative="0.82" duration="5"/>
    <step time="13.00" loaded="934" inserted="108" running="108" waiting="0" ended="0" arrived="0" collisions="0" teleports="0" halting="5" stopped="0" meanWaitingTime="0.58" meanTravelTime="-1.00" meanSpeed="10.98" meanSpeedRelative="0.79" duration="5"/>
    <step time="14.00" loaded="934" inserted="113" running="113" waiting="0" ended="0" arrived="0" collisions="0" teleports="0" halting="7" stopped="0" meanWaitingTime="0.60" meanTravelTime="-1.00" meanSpeed="10.87" meanSpeedRelative="0.78" duration="4"/>
    <step time="15.00" loaded="934" inserted="117" running="117" waiting="0" ended="0" arrived="0" collisions="0" teleports="0" halting="10" stopped="0" meanWaitingTime="0.62" meanTravelTime="-1.00" meanSpeed="10.82" meanSpeedRelative="0.78" duration="4"/>
    <step time="16.00" loaded="934" inserted="119" running="119" waiting="0" ended="0" arrived="0" collisions="0" teleports="0" halting="14" stopped="0" meanWaitingTime="0.61" meanTravelTime="-1.00" meanSpeed="10.43" meanSpeedRelative="0.75" duration="5"/>
    <step time="17.00" loaded="934" inserted="125" running="125" waiting="1" ended="0" arrived="0" collisions="0" teleports="0" halting="17" stopped="0" meanWaitingTime="0.63" meanTravelTime="-1.00" meanSpeed="10.28" meanSpeedRelative="0.74" duration="5"/>
    <step time="18.00" loaded="934" inserted="130" running="130" waiting="0" ended="0" arrived="0" collisions="0" teleports="0" halting="18" stopped="0" meanWaitingTime="0.65" meanTravelTime="-1.00" meanSpeed="9.87" meanSpeedRelative="0.71" duration="6"/>
    <step time="19.00" loaded="934" inserted="135" running="135" waiting="0" ended="0" arrived="0" collisions="0" teleports="0" halting="23" stopped="0" meanWaitingTime="0.67" meanTravelTime="-1.00" meanSpeed="9.43" meanSpeedRelative="0.68" duration="6"/>
    <step time="20.00" loaded="934" inserted="138" running="138" waiting="0" ended="0" arrived="0" collisions="0" teleports="0" halting="30" stopped="0" meanWaitingTime="0.67" meanTravelTime="-1.00" meanSpeed="9.17" meanSpeedRelative="0.66" duration="7"/>
    <step time="21.00" loaded="934" inserted="142" running="142" waiting="0" ended="0" arrived="0" collisions="0" teleports="0" halting="33" stopped="0" meanWaitingTime="0.68" meanTravelTime="-1.00" meanSpeed="9.01" meanSpeedRelative="0.65" duration="7"/>
    <step time="22.00" loaded="934" inserted="146" running="146" waiting="0" ended="0" arrived="0" collisions="0" teleports="0" halting="35" stopped="0" meanWaitingTime="0.69" meanTravelTime="-1.00" meanSpeed="8.90" meanSpeedRelative="0.64" duration="6"/>
    <step time="23.00" loaded="934" inserted="151" running="151" waiting="0" ended="0" arrived="0" collisions="0" teleports="0" halting="38" stopped="0" meanWaitingTime="0.70" meanTravelTime="-1.00" meanSpeed="9.02" meanSpeedRelative="0.65" duration="7"/>
    <step time="24.00" loaded="934" inserted="154" running="154" waiting="0" ended="0" arrived="0" collisions="0" teleports="0" halting="37" stopped="0" meanWaitingTime="0.71" meanTravelTime="-1.00" meanSpeed="9.20" meanSpeedRelative="0.66" duration="7"/>
    <step time="25.00" loaded="934" inserted="158" running="158" waiting="0" ended="0" arrived="0" collisions="0" teleports="0" halting="40" stopped="0" meanWaitingTime="0.72" meanTravelTime="-1.00" meanSpeed="9.31" meanSpeedRelative="0.67" duration="7"/>
    <step time="26.00" loaded="934" inserted="163" running="163" waiting="0" ended="0" arrived="0" collisions="0" teleports="0" halting="42" stopped="0" meanWaitingTime="0.72" meanTravelTime="-1.00" meanSpeed="9.24" meanSpeedRelative="0.66" duration="7"/>
    <step time="27.00" loaded="934" inserted="165" running="165" waiting="0" ended="0" arrived="0" collisions="0" teleports="0" halting="42" stopped="0" meanWaitingTime="0.73" meanTravelTime="-1.00" meanSpeed="9.16" meanSpeedRelative="0.66" duration="8"/>
    <step time="28.00" loaded="934" inserted="170" running="170" waiting="1" ended="0" arrived="0" collisions="0" teleports="0" halting="43" stopped="0" meanWaitingTime="0.74" meanTravelTime="-1.00" meanSpeed="9.11" meanSpeedRelative="0.66" duration="7"/>
    <step time="29.00" loaded="934" inserted="175" running="175" waiting="2" ended="0" arrived="0" collisions="0" teleports="0" halting="43" stopped="0" meanWaitingTime="0.75" meanTravelTime="-1.00" meanSpeed="9.14" meanSpeedRelative="0.66" duration="8"/>
    <step time="30.00" loaded="934" inserted="180" running="180" waiting="1" ended="0" arrived="0" collisions="0" teleports="0" halting="43" stopped="0" meanWaitingTime="0.77" meanTravelTime="-1.00" meanSpeed="9.20" meanSpeedRelative="0.66" duration="9"/>
    <step time="31.00" loaded="934" inserted="182" running="182" waiting="0" ended="0" arrived="0" collisions="0" teleports="0" halting="44" stopped="0" meanWaitingTime="0.77" meanTravelTime="-1.00" meanSpeed="9.03" meanSpeedRelative="0.65" duration="9"/>
    <step time="32.00" loaded="934" inserted="186" running="186" waiting="0" ended="0" arrived="0" collisions="0" teleports="0" halting="46" stopped="0" meanWaitingTime="0.77" meanTravelTime="-1.00" meanSpeed="9.05" meanSpeedRelative="0.65" duration="8"/>
    <step time="33.00" loaded="934" inserted="194" running="194" waiting="0" ended="0" arrived="0" collisions="0" teleports="0" halting="47" stopped="0" meanWaitingTime="0.78" meanTravelTime="-1.00" meanSpeed="8.85" meanSpeedRelative="0.64" duration="9"/>
    <step time="34.00" loaded="934" inserted="197" running="197" waiting="0" ended="0" arrived="0" collisions="0" teleports="0" halting="48" stopped="0" meanWaitingTime="0.79" meanTravelTime="-1.00" meanSpeed="8.99" meanSpeedRelative="0.65" duration="9"/>
    <step time="35.00" loaded="934" inserted="203" running="203" waiting="0" ended="0" arrived="0" collisions="0" teleports="0" halting="50" stopped="0" meanWaitingTime="0.79" meanTravelTime="-1.00" meanSpeed="9.20" meanSpeedRelative="0.66" duration="9"/>
    <step time="36.00" loaded="934" inserted="206" running="206" waiting="0" ended="0" arrived="0" collisions="0" teleports="0" halting="49" stopped="0" meanWaitingTime="0.80" meanTravelTime="-1.00" meanSpeed="9.20" meanSpeedRelative="0.66" duration="10"/>
    <step time="37.00" loaded="934" inserted="209" running="209" waiting="0" ended="0" arrived="0" collisions="0" teleports="0" halting="48" stopped="0" meanWaitingTime="0.80" meanTravelTime="-1.00" meanSpeed="9.19" meanSpeedRelative="0.66" duration="10"/>
    <step time="38.00" loaded="934" inserted="215" running="215" waiting="0" ended="0" arrived="0" collisions="0" teleports="0" halting="51" stopped="0" meanWaitingTime="0.80" meanTravelTime="-1.00" meanSpeed="9.04" meanSpeedRelative="0.65" duration="10"/>
    <step time="39.00" loaded="934" inserted="219" running="219" waiting="0" ended="0" arrived="0" collisions="0" teleports="0" halting="56" stopped="0" meanWaitingTime="0.81" meanTravelTime="-1.00" meanSpeed="9.05" meanSpeedRelative="0.65" duration="10"/>
    <step time="40.00" loaded="934" inserted="221" running="221" waiting="0" ended="0" arrived="0" collisions="0" teleports="0" halting="57" stopped="0" meanWaitingTime="0.81" meanTravelTime="-1.00" meanSpeed="9.07" meanSpeedRelative="0.65" duration="11"/>
    <step time="41.00" loaded="934" inserted="226" running="225" waiting="0" ended="1" arrived="1" collisions="0" teleports="0" halting="60" stopped="0" meanWaitingTime="0.81" meanTravelTime="41.00" meanSpeed="9.09" meanSpeedRelative="0.65" duration="10"/>
    <step time="42.00" loaded="934" inserted="232" running="230" waiting="0" ended="2" arrived="2" collisions="0" teleports="0" halting="60" stopped="0" meanWaitingTime="0.82" meanTravelTime="41.50" meanSpeed="8.92" meanSpeedRelative="0.64" duration="11"/>
    <step time="43.00" loaded="934" inserted="235" running="233" waiting="0" ended="2" arrived="2" collisions="0" teleports="0" halting="60" stopped="0" meanWaitingTime="0.82" meanTravelTime="41.50" meanSpeed="8.98" meanSpeedRelative="0.65" duration="12"/>
    <step time="44.00" loaded="934" inserted="240" running="237" waiting="0" ended="3" arrived="3" collisions="0" teleports="0" halting="62" stopped="0" meanWaitingTime="0.82" meanTravelTime="41.33" meanSpeed="8.94" meanSpeedRelative="0.64" duration="11"/>
    <step time="45.00" loaded="934" inserted="245" running="240" waiting="0" ended="5" arrived="5" collisions="0" teleports="0" halting="63" stopped="0" meanWaitingTime="0.83" meanTravelTime="42.00" meanSpeed="9.12" meanSpeedRelative="0.66" duration="11"/>
    <step time="46.00" loaded="934" inserted="247" running="241" waiting="0" ended="6" arrived="6" collisions="0" teleports="0" halting="62" stopped="0" meanWaitingTime="0.83" meanTravelTime="41.83" meanSpeed="9.22" meanSpeedRelative="0.66" duration="12"/>
    <step time="47.00" loaded="934" inserted="251" running="244" waiting="0" ended="7" arrived="7" collisions="0" teleports="0" halting="61" stopped="0" meanWaitingTime="0.83" meanTravelTime="42.57" meanSpeed="9.15" meanSpeedRelative="0.66" duration="12"/>
    <step time="48.00" loaded="934" inserted="256" running="248" waiting="0" ended="8" arrived="8" collisions="0" teleports="0" halting="63" stopped="0" meanWaitingTime="0.83" meanTravelTime="42.38" meanSpeed="9.15" meanSpeedRelative="0.66" duration="12"/>
    <step time="49.00" loaded="934" inserted="262" running="251" waiting="0" ended="11" arrived="11" collisions="0" teleports="0" halting="62" stopped="0" meanWaitingTime="0.83" meanTravelTime="42.55" meanSpeed="8.89" meanSpeedRelative="0.64" duration="13"/>
    <step time="50.00" loaded="934" inserted="266" running="254" waiting="0" ended="12" arrived="12" collisions="0" teleports="0" halting="63" stopped="0" meanWaitingTime="0.83" meanTravelTime="42.25" meanSpeed="8.95" meanSpeedRelative="0.64" duration="13"/>
    <step time="51.00" loaded="934" inserted="270" running="257" waiting="0" ended="13" arrived="13" collisions="0" teleports="0" halting="70" stopped="0" meanWaitingTime="0.84" meanTravelTime="42.15" meanSpeed="8.84" meanSpeedRelative="0.64" duration="13"/>
    <step time="52.00" loaded="934" inserted="275" running="260" waiting="0" ended="15" arrived="15" collisions="0" teleports="0" halting="70" stopped="0" meanWaitingTime="0.84" meanTravelTime="41.27" meanSpeed="8.76" meanSpeedRelative="0.63" duration="13"/>
    <step time="53.00" loaded="934" inserted="279" running="263" waiting="0" ended="16" arrived="16" collisions="0" teleports="0" halting="70" stopped="0" meanWaitingTime="0.84" meanTravelTime="41.25" meanSpeed="8.67" meanSpeedRelative="0.62" duration="13"/>
    <step time="54.00" loaded="934" inserted="282" running="265" waiting="0" ended="17" arrived="17" collisions="0" teleports="0" halting="71" stopped="0" meanWaitingTime="0.84" meanTravelTime="41.00" meanSpeed="8.71" meanSpeedRelative="0.63" duration="13"/>
    <step time="55.00" loaded="934" inserted="286" running="268" waiting="0" ended="18" arrived="18" collisions="0" teleports="0" halting="72" stopped="0" meanWaitingTime="0.85" meanTravelTime="41.39" meanSpeed="8.60" meanSpeedRelative="0.62" duration="14"/>
    <step time="56.00" loaded="934" inserted="293" running="273" waiting="0" ended="20" arrived="20" collisions="0" teleports="0" halting="77" stopped="0" meanWaitingTime="0.85" meanTravelTime="41.40" meanSpeed="8.69" meanSpeedRelative="0.63" duration="14"/>
    <step time="57.00" loaded="934" inserted="299" running="278" waiting="0" ended="21" arrived="21" collisions="0" teleports="0" halting="81" stopped="0" meanWaitingTime="0.85" meanTravelTime="41.48" meanSpeed="8.74" meanSpeedRelative="0.63" duration="14"/>
    <step time="58.00" loaded="934" inserted="304" running="282" waiting="0" ended="22" arrived="22" collisions="0" teleports="0" halting="82" stopped="0" meanWaitingTime="0.86" meanTravelTime="41.45" meanSpeed="8.53" meanSpeedRelative="0.61" duration="14"/>
    <step time="59.00" loaded="934" inserted="306" running="284" waiting="0" ended="22" arrived="22" collisions="0" teleports="0" halting="81" stopped="0" meanWaitingTime="0.86" meanTravelTime="41.45" meanSpeed="8.55" meanSpeedRelative="0.62" duration="15"/>
    <step time="60.00" loaded="934" inserted="312" running="288" waiting="0" ended="24" arrived="24" collisions="0" teleports="0" halting="85" stopped="0" meanWaitingTime="0.86" meanTravelTime="41.42" meanSpeed="8.46" meanSpeedRelative="0.61" duration="14"/>
    <step time="61.00" loaded="934" inserted="315" running="291" waiting="0" ended="24" arrived="24" collisions="0" teleports="0" halting="87" stopped="0" meanWaitingTime="0.86" meanTravelTime="41.42" meanSpeed="8.55" meanSpeedRelative="0.62" duration="15"/>
    <step time="62.00" loaded="934" inserted="317" running="292" waiting="0" ended="25" arrived="25" collisions="0" teleports="0" halting="87" stopped="0" meanWaitingTime="0.86" meanTravelTime="41.40" meanSpeed="8.47" meanSpeedRelative="0.61" duration="15"/>
    <step time="63.00" loaded="934" inserted="323" running="298" waiting="0" ended="25" arrived="25" collisions="0" teleports="0" halting="92" stopped="0" meanWaitingTime="0.86" meanTravelTime="41.40" meanSpeed="8.30" meanSpeedRelative="0.60" duration="15"/>
    <step time="64.00" loaded="934" inserted="327" running="302" waiting="0" ended="25" arrived="25" collisions="0" teleports="0" halting="99" stopped="0" meanWaitingTime="0.86" meanTravelTime="41.40" meanSpeed="8.08" meanSpeedRelative="0.58" duration="15"/>
    <step time="65.00" loaded="934" inserted="331" running="306" waiting="0" ended="25" arrived="25" collisions="0" teleports="0" halting="99" stopped="0" meanWaitingTime="0.86" meanTravelTime="41.40" meanSpeed="8.06" meanSpeedRelative="0.58" duration="14"/>
    <step time="66.00" loaded="934" inserted="337" running="310" waiting="0" ended="27" arrived="27" collisions="0" teleports="0" halting="101" stopped="0" meanWaitingTime="0.86" meanTravelTime="41.52" meanSpeed="8.03" meanSpeedRelative="0.58" duration="15"/>
    <step time="67.00" loaded="934" inserted="344" running="315" waiting="0" ended="29" arrived="29" collisions="0" teleports="0" halting="97" stopped="0" meanWaitingTime="0.87" meanTravelTime="41.59" meanSpeed="8.05" meanSpeedRelative="0.58" duration="17"/>
    <step time="68.00" loaded="934" inserted="346" running="315" waiting="0" ended="31" arrived="31" collisions="0" teleports="0" halting="97" stopped="0" meanWaitingTime="0.87" meanTravelTime="41.87" meanSpeed="8.25" meanSpeedRelative="0.59" duration="17"/>
    <step time="69.00" loaded="934" inserted="350" running="318" waiting="0" ended="32" arrived="32" collisions="0" teleports="0" halting="95" stopped="0" meanWaitingTime="0.87" meanTravelTime="41.84" meanSpeed="8.40" meanSpeedRelative="0.60" duration="15"/>
    <step time="70.00" loaded="934" inserted="356" running="323" waiting="0" ended="33" arrived="33" collisions="0" teleports="0" halting="95" stopped="0" meanWaitingTime="0.87" meanTravelTime="41.94" meanSpeed="8.35" meanSpeedRelative="0.60" duration="16"/>
    <step time="71.00" loaded="934" inserted="360" running="326" waiting="0" ended="34" arrived="34" collisions="0" teleports="0" halting="94" stopped="0" meanWaitingTime="0.87" meanTravelTime="41.91" meanSpeed="8.21" meanSpeedRelative="0.59" duration="16"/>
    <step time="72.00" loaded="934" inserted="364" running="330" waiting="0" ended="34" arrived="34" collisions="0" teleports="0" halting="98" stopped="0" meanWaitingTime="0.87" meanTravelTime="41.91" meanSpeed="8.16" meanSpeedRelative="0.59" duration="17"/>
    <step time="73.00" loaded="934" inserted="368" running="333" waiting="0" ended="35" arrived="35" collisions="0" teleports="0" halting="105" stopped="0" meanWaitingTime="0.88" meanTravelTime="41.94" meanSpeed="8.09" meanSpeedRelative="0.58" duration="17"/>
    <step time="74.00" loaded="934" inserted="372" running="337" waiting="0" ended="35" arrived="35" collisions="0" teleports="0" halting="107" stopped="0" meanWaitingTime="0.88" meanTravelTime="41.94" meanSpeed="8.16" meanSpeedRelative="0.59" duration="18"/>
    <step time="75.00" loaded="934" inserted="375" running="339" waiting="0" ended="36" arrived="36" collisions="0" teleports="0" halting="110" stopped="0" meanWaitingTime="0.88" meanTravelTime="41.92" meanSpeed="8.17" meanSpeedRelative="0.59" duration="18"/>
    <step time="76.00" loaded="934" inserted="382" running="345" waiting="0" ended="37" arrived="37" collisions="0" teleports="0" halting="112" stopped="0" meanWaitingTime="0.88" meanTravelTime="41.95" meanSpeed="8.05" meanSpeedRelative="0.58" duration="18"/>
    <step time="77.00" loaded="934" inserted="385" running="344" waiting="0" ended="41" arrived="41" collisions="0" teleports="0" halting="115" stopped="0" meanWaitingTime="0.88" meanTravelTime="41.88" meanSpeed="8.02" meanSpeedRelative="0.58" duration="19"/>
    <step time="78.00" loaded="934" inserted="389" running="347" waiting="0" ended="42" arrived="42" collisions="0" teleports="0" halting="115" stopped="0" meanWaitingTime="0.88" meanTravelTime="41.86" meanSpeed="8.00" meanSpeedRelative="0.58" duration="19"/>
    <step time="79.00" loaded="934" inserted="394" running="351" waiting="0" ended="43" arrived="43" collisions="0" teleports="0" halting="117" stopped="0" meanWaitingTime="0.88" meanTravelTime="41.98" meanSpeed="8.05" meanSpeedRelative="0.58" duration="20"/>
    <step time="80.00" loaded="934" inserted="397" running="354" waiting="0" ended="43" arrived="43" collisions="0" teleports="0" halting="118" stopped="0" meanWaitingTime="0.88" meanTravelTime="41.98" meanSpeed="8.14" meanSpeedRelative="0.59" duration="20"/>
    <step time="81.00" loaded="934" inserted="402" running="358" waiting="0" ended="44" arrived="44" collisions="0" teleports="0" halting="117" stopped="0" meanWaitingTime="0.88" meanTravelTime="42.23" meanSpeed="8.18" meanSpeedRelative="0.59" duration="19"/>
    <step time="82.00" loaded="934" inserted="408" running="364" waiting="0" ended="44" arrived="44" collisions="0" teleports="0" halting="118" stopped="0" meanWaitingTime="0.88" meanTravelTime="42.23" meanSpeed="8.11" meanSpeedRelative="0.58" duration="20"/>
    <step time="83.00" loaded="934" inserted="411" running="367" waiting="0" ended="44" arrived="44" collisions="0" teleports="0" halting="119" stopped="0" meanWaitingTime="0.89" meanTravelTime="42.23" meanSpeed="8.20" meanSpeedRelative="0.59" duration="26"/>
    <step time="84.00" loaded="934" inserted="418" running="374" waiting="0" ended="44" arrived="44" collisions="0" teleports="0" halting="126" stopped="0" meanWaitingTime="0.89" meanTravelTime="42.23" meanSpeed="8.00" meanSpeedRelative="0.58" duration="19"/>
    <step time="85.00" loaded="934" inserted="424" running="380" waiting="0" ended="44" arrived="44" collisions="0" teleports="0" halting="127" stopped="0" meanWaitingTime="0.89" meanTravelTime="42.23" meanSpeed="7.75" meanSpeedRelative="0.56" duration="20"/>
    <step time="86.00" loaded="934" inserted="428" running="384" waiting="0" ended="44" arrived="44" collisions="0" teleports="0" halting="130" stopped="0" meanWaitingTime="0.89" meanTravelTime="42.23" meanSpeed="7.62" meanSpeedRelative="0.55" duration="21"/>
    <step time="87.00" loaded="934" inserted="433" running="389" waiting="0" ended="44" arrived="44" collisions="0" teleports="0" halting="138" stopped="0" meanWaitingTime="0.89" meanTravelTime="42.23" meanSpeed="7.73" meanSpeedRelative="0.56" duration="22"/>
    <step time="88.00" loaded="934" inserted="437" running="392" waiting="0" ended="45" arrived="45" collisions="0" teleports="0" halting="139" stopped="0" meanWaitingTime="0.89" meanTravelTime="43.11" meanSpeed="7.74" meanSpeedRelative="0.56" duration="22"/>
    <step time="89.00" loaded="934" inserted="440" running="395" waiting="0" ended="45" arrived="45" collisions="0" teleports="0" halting="145" stopped="0" meanWaitingTime="0.89" meanTravelTime="43.11" meanSpeed="7.64" meanSpeedRelative="0.55" duration="22"/>
    <step time="90.00" loaded="934" inserted="446" running="398" waiting="0" ended="48" arrived="48" collisions="0" teleports="0" halting="146" stopped="0" meanWaitingTime="0.89" meanTravelTime="45.23" meanSpeed="7.49" meanSpeedRelative="0.54" duration="22"/>
    <step time="91.00" loaded="934" inserted="448" running="397" waiting="0" ended="51" arrived="51" collisions="0" teleports="0" halting="149" stopped="0" meanWaitingTime="0.90" meanTravelTime="45.76" meanSpeed="7.49" meanSpeedRelative="0.54" duration="21"/>
    <step time="92.00" loaded="934" inserted="450" running="398" waiting="0" ended="52" arrived="52" collisions="0" teleports="0" halting="148" stopped="0" meanWaitingTime="0.90" meanTravelTime="45.90" meanSpeed="7.48" meanSpeedRelative="0.54" duration="21"/>
    <step time="93.00" loaded="934" inserted="455" running="402" waiting="0" ended="53" arrived="53" collisions="0" teleports="0" halting="156" stopped="0" meanWaitingTime="0.90" meanTravelTime="46.74" meanSpeed="7.36" meanSpeedRelative="0.53" duration="22"/>
    <step time="94.00" loaded="934" inserted="459" running="405" waiting="0" ended="54" arrived="54" collisions="0" teleports="0" halting="160" stopped="0" meanWaitingTime="0.90" meanTravelTime="47.61" meanSpeed="7.27" meanSpeedRelative="0.52" duration="22"/>
    <step time="95.00" loaded="934" inserted="464" running="409" waiting="0" ended="55" arrived="55" collisions="0" teleports="0" halting="167" stopped="0" meanWaitingTime="0.90" meanTravelTime="47.42" meanSpeed="7.12" meanSpeedRelative="0.51" duration="22"/>
    <step time="96.00" loaded="934" inserted="470" running="415" waiting="0" ended="55" arrived="55" collisions="0" teleports="0" halting="167" stopped="0" meanWaitingTime="0.90" meanTravelTime="47.42" meanSpeed="7.13" meanSpeedRelative="0.51" duration="22"/>
    <step time="97.00" loaded="934" inserted="476" running="421" waiting="0" ended="55" arrived="55" collisions="0" teleports="0" halting="170" stopped="0" meanWaitingTime="0.90" meanTravelTime="47.42" meanSpeed="7.09" meanSpeedRelative="0.51" duration="23"/>
    <step time="98.00" loaded="934" inserted="479" running="422" waiting="0" ended="57" arrived="57" collisions="0" teleports="0" halting="170" stopped="0" meanWaitingTime="0.90" meanTravelTime="49.19" meanSpeed="7.09" meanSpeedRelative="0.51" duration="24"/>
    <step time="99.00" loaded="934" inserted="483" running="424" waiting="0" ended="59" arrived="59" collisions="0" teleports="0" halting="177" stopped="0" meanWaitingTime="0.90" meanTravelTime="50.64" meanSpeed="7.08" meanSpeedRelative="0.51" duration="32"/>
    <step time="100.00" loaded="934" inserted="489" running="427" waiting="0" ended="62" arrived="62" collisions="0" teleports="0" halting="182" stopped="0" meanWaitingTime="0.90" meanTravelTime="51.95" meanSpeed="7.03" meanSpeedRelative="0.51" duration="24"/>
    <step time="101.00" loaded="934" inserted="492" running="429" waiting="0" ended="63" arrived="63" collisions="0" teleports="0" halting="185" stopped="0" meanWaitingTime="0.90" meanTravelTime="52.68" meanSpeed="6.95" meanSpeedRelative="0.50" duration="24"/>
    <step time="102.00" loaded="934" inserted="495" running="428" waiting="0" ended="67" arrived="67" collisions="0" teleports="0" halting="187" stopped="0" meanWaitingTime="0.90" meanTravelTime="55.27" meanSpeed="6.86" meanSpeedRelative="0.49" duration="24"/>
    <step time="103.00" loaded="934" inserted="498" running="430" waiting="0" ended="68" arrived="68" collisions="0" teleports="0" halting="193" stopped="0" meanWaitingTime="0.90" meanTravelTime="55.88" meanSpeed="6.79" meanSpeedRelative="0.49" duration="25"/>
    <step time="104.00" loaded="934" inserted="505" running="437" waiting="0" ended="68" arrived="68" collisions="0" teleports="0" halting="196" stopped="0" meanWaitingTime="0.90" meanTravelTime="55.88" meanSpeed="6.70" meanSpeedRelative="0.48" duration="26"/>
    <step time="105.00" loaded="934" inserted="509" running="438" waiting="0" ended="71" arrived="71" collisions="0" teleports="0" halting="195" stopped="0" meanWaitingTime="0.91" meanTravelTime="57.66" meanSpeed="6.53" meanSpeedRelative="0.47" duration="27"/>
    <step time="106.00" loaded="934" inserted="516" running="444" waiting="0" ended="72" arrived="72" collisions="0" teleports="0" halting="204" stopped="0" meanWaitingTime="0.91" meanTravelTime="58.22" meanSpeed="6.37" meanSpeedRelative="0.46" duration="26"/>
    <step time="107.00" loaded="934" inserted="521" running="447" waiting="0" ended="74" arrived="74" collisions="0" teleports="0" halting="208" stopped="0" meanWaitingTime="0.91" meanTravelTime="59.42" meanSpeed="6.27" meanSpeedRelative="0.45" duration="27"/>
    <step time="108.00" loaded="934" inserted="522" running="445" waiting="0" ended="77" arrived="77" collisions="0" teleports="0" halting="210" stopped="0" meanWaitingTime="0.91" meanTravelTime="61.03" meanSpeed="6.20" meanSpeedRelative="0.45" duration="27"/>
    <step time="109.00" loaded="934" inserted="527" running="450" waiting="0" ended="77" arrived="77" collisions="0" teleports="0" halting="215" stopped="0" meanWaitingTime="0.91" meanTravelTime="61.03" meanSpeed="6.27" meanSpeedRelative="0.45" duration="28"/>
    <step time="110.00" loaded="934" inserted="529" running="449" waiting="0" ended="80" arrived="80" collisions="0" teleports="0" halting="217" stopped="0" meanWaitingTime="0.91" meanTravelTime="62.45" meanSpeed="6.34" meanSpeedRelative="0.46" duration="28"/>
    <step time="111.00" loaded="934" inserted="536" running="454" waiting="0" ended="82" arrived="82" collisions="0" teleports="0" halting="220" stopped="0" meanWaitingTime="0.91" meanTravelTime="63.21" meanSpeed="6.23" meanSpeedRelative="0.45" duration="26"/>
    <step time="112.00" loaded="934" inserted="540" running="458" waiting="0" ended="82" arrived="82" collisions="0" teleports="0" halting="219" stopped="0" meanWaitingTime="0.91" meanTravelTime="63.21" meanSpeed="6.17" meanSpeedRelative="0.44" duration="28"/>
    <step time="113.00" loaded="934" inserted="545" running="463" waiting="0" ended="82" arrived="82" collisions="0" teleports="0" halting="219" stopped="0" meanWaitingTime="0.91" meanTravelTime="63.21" meanSpeed="6.18" meanSpeedRelative="0.45" duration="28"/>
    <step time="114.00" loaded="934" inserted="551" running="467" waiting="0" ended="84" arrived="84" collisions="0" teleports="0" halting="222" stopped="0" meanWaitingTime="0.91" meanTravelTime="63.39" meanSpeed="6.19" meanSpeedRelative="0.45" duration="29"/>
    <step time="115.00" loaded="934" inserted="557" running="470" waiting="0" ended="87" arrived="87" collisions="0" teleports="0" halting="224" stopped="0" meanWaitingTime="0.91" meanTravelTime="63.99" meanSpeed="6.03" meanSpeedRelative="0.43" duration="29"/>
    <step time="116.00" loaded="934" inserted="560" running="470" waiting="0" ended="90" arrived="90" collisions="0" teleports="0" halting="229" stopped="0" meanWaitingTime="0.91" meanTravelTime="65.20" meanSpeed="5.96" meanSpeedRelative="0.43" duration="28"/>
    <step time="117.00" loaded="934" inserted="563" running="470" waiting="0" ended="93" arrived="93" collisions="0" teleports="0" halting="231" stopped="0" meanWaitingTime="0.91" meanTravelTime="66.31" meanSpeed="5.93" meanSpeedRelative="0.43" duration="29"/>
    <step time="118.00" loaded="934" inserted="568" running="472" waiting="0" ended="96" arrived="96" collisions="0" teleports="0" halting="236" stopped="0" meanWaitingTime="0.91" meanTravelTime="67.46" meanSpeed="5.86" meanSpeedRelative="0.42" duration="28"/>
    <step time="119.00" loaded="934" inserted="571" running="474" waiting="0" ended="97" arrived="97" collisions="0" teleports="0" halting="238" stopped="0" meanWaitingTime="0.91" meanTravelTime="67.76" meanSpeed="5.93" meanSpeedRelative="0.43" duration="28"/>
    <step time="120.00" loaded="934" inserted="576" running="478" waiting="0" ended="98" arrived="98" collisions="0" teleports="0" halting="239" stopped="0" meanWaitingTime="0.91" meanTravelTime="68.06" meanSpeed="5.83" meanSpeedRelative="0.42" duration="28"/>
    <step time="121.00" loaded="934" inserted="580" running="481" waiting="0" ended="99" arrived="99" collisions="0" teleports="0" halting="240" stopped="0" meanWaitingTime="0.91" meanTravelTime="68.44" meanSpeed="5.71" meanSpeedRelative="0.41" duration="28"/>
    <step time="122.00" loaded="934" inserted="586" running="485" waiting="0" ended="101" arrived="101" collisions="0" teleports="0" halting="246" stopped="0" meanWaitingTime="0.91" meanTravelTime="69.10" meanSpeed="5.56" meanSpeedRelative="0.40" duration="28"/>
    <step time="123.00" loaded="934" inserted="592" running="486" waiting="0" ended="106" arrived="106" collisions="0" teleports="0" halting="249" stopped="0" meanWaitingTime="0.92" meanTravelTime="70.69" meanSpeed="5.39" meanSpeedRelative="0.39" duration="30"/>
    <step time="124.00" loaded="934" inserted="593" running="487" waiting="0" ended="106" arrived="106" collisions="0" teleports="0" halting="239" stopped="0" meanWaitingTime="0.92" meanTravelTime="70.69" meanSpeed="5.42" meanSpeedRelative="0.39" duration="30"/>
    <step time="125.00" loaded="934" inserted="599" running="493" waiting="0" ended="106" arrived="106" collisions="0" teleports="0" halting="228" stopped="0" meanWaitingTime="0.92" meanTravelTime="70.69" meanSpeed="5.34" meanSpeedRelative="0.38" duration="31"/>
    <step time="126.00" loaded="934" inserted="602" running="493" waiting