<?xml version="1.0" encoding="UTF-8"?>

<!-- generated on 2025-05-20 01:18:42 by Eclipse SUMO sumo Version 1.19.0
<configuration xmlns:xsi="http://www.w3.org/2001/XMLSchema-instance" xsi:noNamespaceSchemaLocation="http://sumo.dlr.de/xsd/sumoConfiguration.xsd">

    <input>
        <net-file value="map.net.xml"/>
        <route-files value="demand.rou.alt.xml"/>
        <additional-files value="detector_temp_20250520_011841.add.xml"/>
    </input>

    <output>
        <summary-output value="results\20250520_011841\summary_out_20250520_011841.xml"/>
        <tripinfo-output value="results\20250520_011841\tripinfo_out_20250520_011841.xml"/>
        <statistic-output value="results\20250520_011841\statistic_out_20250520_011841.xml"/>
    </output>

    <time>
        <step-length value="0.5"/>
    </time>

    <processing>
        <threads value="4"/>
        <lateral-resolution value="0.2"/>
        <ignore-junction-blocker value="300"/>
        <collision.action value="none"/>
    </processing>

    <traci_server>
        <remote-port value="60328"/>
    </traci_server>

</configuration>
-->

<statistics xmlns:xsi="http://www.w3.org/2001/XMLSchema-instance" xsi:noNamespaceSchemaLocation="http://sumo.dlr.de/xsd/statistic_file.xsd">
    <performance clockBegin="279286.60" clockEnd="288299.45" clockDuration="9012.85" traciDuration="7001.47" realTimeFactor="1.73" vehicleUpdatesPerSecond="3975.45" personUpdatesPerSecond="0.00" begin="0.00" end="15558.00" duration="15558.00"/>
    <vehicles loaded="82128" inserted="82128" running="0" waiting="0"/>
    <teleports total="101" jam="0" yield="101" wrongLane="0"/>
    <safety collisions="0" emergencyStops="0" emergencyBraking="0"/>
    <persons loaded="0" running="0" jammed="0"/>
    <personTeleports total="0" abortWait="0" wrongDest="0"/>
    <vehicleTripStatistics count="82128" routeLength="983.98" speed="6.86" duration="218.13" waitingTime="118.77" timeLoss="146.45" departDelay="162.91" departDelayWaiting="-1.00" totalTravelTime="17915068.00" totalDepartDelay="13379837.89"/>
    <pedestrianStatistics number="0" routeLength="0.00" duration="0.00" timeLoss="0.00"/>
    <rideStatistics number="0"/>
    <transportStatistics number="0"/>
</statistics>
